{
    "rpc": [
        {
            "slug": "alchemy-mainnet-free-recent-state",
            "provider": "Alchemy",
            "plan": "Free",
            "nodeType": "Recent-State",
            "chain": "mainnet",
            "address": null,
            "accessPrice": "$0",
            "queryPrice": "$0/1M request",
            "uptimeSla": null,
            "bandwidthSla": null,
            "blocksBehindSla": null,
            "trial": false,
            "availableApis": [
                "eth",
                "web3",
                "net",
                "debug",
                "trace",
                "nft",
                "transfer",
                "tokens",
                "node"
            ],
            "limitations": [
                "25 reqs/sec",
                "30M CU/mo"
            ],
            "securityImprovements": [
                "TX simulation",
                "DDoS Protection",
                "IP Protection"
            ],
            "monitoringAndAnalytics": [
                "Basic monitoring",
                "Usage analytics"
            ],
            "regions": [
                "Global"
            ],
            "verifiedUptime": null,
            "verifiedLatency": null,
            "verifiedBlocksBehindAvg": null,
            "starred": false,
            "actionButtons": [
                "[Website](https://www.alchemy.com/rpc/aptos)",
                "[Docs](https://www.alchemy.com/docs/reference/aptos-api-quickstart)"
            ]
        },
        {
            "slug": "alchemy-mainnet-pay-as-you-go-recent-state",
            "provider": "Alchemy",
            "plan": "Pay-as-you-go",
            "nodeType": "Recent-State",
            "chain": "mainnet",
            "address": null,
            "accessPrice": "$5/$45/$215/$415/$815/$2K",
            "queryPrice": "$0.40/$0.45/1M CUs",
            "uptimeSla": "99.99%",
            "bandwidthSla": null,
            "blocksBehindSla": null,
            "trial": false,
            "availableApis": [
                "eth",
                "web3",
                "net",
                "debug",
                "trace",
                "nft",
                "transfer",
                "tokens",
                "node"
            ],
            "limitations": [
                "300 req/sec"
            ],
            "securityImprovements": [
                "TX simulation",
                "DDoS Protection",
                "IP Protection",
                "SAML SSO"
            ],
            "monitoringAndAnalytics": [
                "Usage analytics",
                "Custom alerts",
                "Reporting",
                "Custom monitoring",
                "Advanced analytics"
            ],
            "regions": [
                "Global"
            ],
            "verifiedUptime": null,
            "verifiedLatency": null,
            "verifiedBlocksBehindAvg": null,
            "starred": false,
            "actionButtons": [
                "[Buy](https://www.alchemy.com/pricing)",
                "[Docs](https://www.alchemy.com/docs/reference/aptos-api-quickstart)"
            ]
        },
        {
            "slug": "alchemy-mainnet-enterprise-recent-state",
            "provider": "Alchemy",
            "plan": "Enterprise",
            "nodeType": "Recent-State",
            "chain": "mainnet",
            "address": null,
            "accessPrice": "Custom",
            "queryPrice": "Custom pricing",
            "uptimeSla": "99.99%",
            "bandwidthSla": null,
            "blocksBehindSla": null,
            "trial": false,
            "availableApis": [
                "eth",
                "web3",
                "net",
                "debug",
                "trace",
                "nft",
                "transfer",
                "tokens",
                "node"
            ],
            "limitations": [
                "custom limits"
            ],
            "securityImprovements": [
                "TX simulation",
                "DDoS Protection",
                "IP Protection",
                "Dedicated infrastructure"
            ],
            "monitoringAndAnalytics": [
                "Usage analytics",
                "Advanced analytics",
                "Custom dashboards",
                "Engineering support"
            ],
            "regions": [
                "Global"
            ],
            "verifiedUptime": null,
            "verifiedLatency": null,
            "verifiedBlocksBehindAvg": null,
            "starred": false,
            "actionButtons": [
                "[Contact](https://www.alchemy.com/contact-sales)",
                "[Docs](https://www.alchemy.com/docs/reference/aptos-api-quickstart)"
            ]
        },
        {
            "slug": "alchemy-testnet-free-recent-state",
            "provider": "Alchemy",
            "plan": "Free",
            "nodeType": "Recent-State",
            "chain": "testnet",
            "address": null,
            "accessPrice": "$0",
            "queryPrice": "$0/1M request",
            "uptimeSla": null,
            "bandwidthSla": null,
            "blocksBehindSla": null,
            "trial": false,
            "availableApis": [
                "eth",
                "web3",
                "net",
                "debug",
                "trace",
                "nft",
                "transfer",
                "tokens",
                "node"
            ],
            "limitations": [
                "25 reqs/sec",
                "30M CU/mo"
            ],
            "securityImprovements": [
                "TX simulation",
                "DDoS Protection",
                "IP Protection"
            ],
            "monitoringAndAnalytics": [
                "Basic monitoring",
                "Usage analytics"
            ],
            "regions": [
                "Global"
            ],
            "verifiedUptime": null,
            "verifiedLatency": null,
            "verifiedBlocksBehindAvg": null,
            "starred": false,
            "actionButtons": [
                "[Website](https://www.alchemy.com/rpc/aptos-testnet)",
                "[Docs](https://www.alchemy.com/docs/reference/aptos-api-quickstart)"
            ]
        },
        {
            "slug": "alchemy-testnet-pay-as-you-go-recent-state",
            "provider": "Alchemy",
            "plan": "Pay-as-you-go",
            "nodeType": "Recent-State",
            "chain": "testnet",
            "address": null,
            "accessPrice": "$5/$45/$215/$415/$815/$2K",
            "queryPrice": "$0.40/$0.45/1M CUs",
            "uptimeSla": "99.99%",
            "bandwidthSla": null,
            "blocksBehindSla": null,
            "trial": false,
            "availableApis": [
                "eth",
                "web3",
                "net",
                "debug",
                "trace",
                "nft",
                "transfer",
                "tokens",
                "node"
            ],
            "limitations": [
                "300 req/sec"
            ],
            "securityImprovements": [
                "TX simulation",
                "DDoS Protection",
                "IP Protection",
                "SAML SSO"
            ],
            "monitoringAndAnalytics": [
                "Usage analytics",
                "Custom alerts",
                "Reporting",
                "Custom monitoring",
                "Advanced analytics"
            ],
            "regions": [
                "Global"
            ],
            "verifiedUptime": null,
            "verifiedLatency": null,
            "verifiedBlocksBehindAvg": null,
            "starred": false,
            "actionButtons": [
                "[Buy](https://www.alchemy.com/pricing)",
                "[Docs](https://www.alchemy.com/docs/reference/aptos-api-quickstart)"
            ]
        },
        {
            "slug": "alchemy-testnet-enterprise-recent-state",
            "provider": "Alchemy",
            "plan": "Enterprise",
            "nodeType": "Recent-State",
            "chain": "testnet",
            "address": null,
            "accessPrice": "Custom",
            "queryPrice": "Custom pricing",
            "uptimeSla": "99.99%",
            "bandwidthSla": null,
            "blocksBehindSla": null,
            "trial": false,
            "availableApis": [
                "eth",
                "web3",
                "net",
                "debug",
                "trace",
                "nft",
                "transfer",
                "tokens",
                "node"
            ],
            "limitations": [
                "custom limits"
            ],
            "securityImprovements": [
                "TX simulation",
                "DDoS Protection",
                "IP Protection",
                "Dedicated infrastructure"
            ],
            "monitoringAndAnalytics": [
                "Usage analytics",
                "Advanced analytics",
                "Custom dashboards",
                "Engineering support"
            ],
            "regions": [
                "Global"
            ],
            "verifiedUptime": null,
            "verifiedLatency": null,
            "verifiedBlocksBehindAvg": null,
            "starred": false,
            "actionButtons": [
                "[Contact](https://www.alchemy.com/contact-sales)",
                "[Docs](https://www.alchemy.com/docs/reference/aptos-api-quickstart)"
            ]
        },
        {
            "slug": "alchemy-mainnet-free-full-archive",
            "provider": "Alchemy",
            "plan": "Free",
            "nodeType": "Full Archive",
            "chain": "mainnet",
            "address": null,
            "accessPrice": "$0",
            "queryPrice": "$0/1M request",
            "uptimeSla": null,
            "bandwidthSla": null,
            "blocksBehindSla": null,
            "trial": false,
            "availableApis": [
                "eth",
                "web3",
                "net",
                "debug",
                "trace",
                "nft",
                "transfer",
                "tokens",
                "node"
            ],
            "limitations": [
                "25 reqs/sec",
                "30M CU/mo"
            ],
            "securityImprovements": [
                "TX simulation",
                "DDoS Protection",
                "IP Protection"
            ],
            "monitoringAndAnalytics": [
                "Basic monitoring",
                "Usage analytics"
            ],
            "regions": [
                "Global"
            ],
            "verifiedUptime": null,
            "verifiedLatency": null,
            "verifiedBlocksBehindAvg": null,
            "starred": false,
            "actionButtons": [
                "[Website](https://www.alchemy.com/rpc/aptos)",
                "[Docs](https://www.alchemy.com/docs/reference/aptos-api-quickstart)"
            ]
        },
        {
            "slug": "alchemy-mainnet-pay-as-you-go-full-archive",
            "provider": "Alchemy",
            "plan": "Pay-as-you-go",
            "nodeType": "Full Archive",
            "chain": "mainnet",
            "address": null,
            "accessPrice": "$5/$45/$215/$415/$815/$2K",
            "queryPrice": "$0.40/$0.45/1M CUs",
            "uptimeSla": "99.99%",
            "bandwidthSla": null,
            "blocksBehindSla": null,
            "trial": false,
            "availableApis": [
                "eth",
                "web3",
                "net",
                "debug",
                "trace",
                "nft",
                "transfer",
                "tokens",
                "node"
            ],
            "limitations": [
                "300 req/sec"
            ],
            "securityImprovements": [
                "TX simulation",
                "DDoS Protection",
                "IP Protection",
                "SAML SSO"
            ],
            "monitoringAndAnalytics": [
                "Usage analytics",
                "Custom alerts",
                "Reporting",
                "Custom monitoring",
                "Advanced analytics"
            ],
            "regions": [
                "Global"
            ],
            "verifiedUptime": null,
            "verifiedLatency": null,
            "verifiedBlocksBehindAvg": null,
            "starred": false,
            "actionButtons": [
                "[Buy](https://www.alchemy.com/pricing)",
                "[Docs](https://www.alchemy.com/docs/reference/aptos-api-quickstart)"
            ]
        },
        {
            "slug": "alchemy-mainnet-enterprise-full-archive",
            "provider": "Alchemy",
            "plan": "Enterprise",
            "nodeType": "Full Archive",
            "chain": "mainnet",
            "address": null,
            "accessPrice": "Custom",
            "queryPrice": "Custom pricing",
            "uptimeSla": "99.99%",
            "bandwidthSla": null,
            "blocksBehindSla": null,
            "trial": false,
            "availableApis": [
                "eth",
                "web3",
                "net",
                "debug",
                "trace",
                "nft",
                "transfer",
                "tokens",
                "node"
            ],
            "limitations": [
                "custom limits"
            ],
            "securityImprovements": [
                "TX simulation",
                "DDoS Protection",
                "IP Protection",
                "Dedicated infrastructure"
            ],
            "monitoringAndAnalytics": [
                "Usage analytics",
                "Advanced analytics",
                "Custom dashboards",
                "Engineering support"
            ],
            "regions": [
                "Global"
            ],
            "verifiedUptime": null,
            "verifiedLatency": null,
            "verifiedBlocksBehindAvg": null,
            "starred": false,
            "actionButtons": [
                "[Contact](https://www.alchemy.com/contact-sales)",
                "[Docs](https://www.alchemy.com/docs/reference/aptos-api-quickstart)"
            ]
        },
        {
            "slug": "alchemy-testnet-free-full-archive",
            "provider": "Alchemy",
            "plan": "Free",
            "nodeType": "Full Archive",
            "chain": "testnet",
            "address": null,
            "accessPrice": "$0",
            "queryPrice": "$0/1M request",
            "uptimeSla": null,
            "bandwidthSla": null,
            "blocksBehindSla": null,
            "trial": false,
            "availableApis": [
                "eth",
                "web3",
                "net",
                "debug",
                "trace",
                "nft",
                "transfer",
                "tokens",
                "node"
            ],
            "limitations": [
                "25 reqs/sec",
                "30M CU/mo"
            ],
            "securityImprovements": [
                "TX simulation",
                "DDoS Protection",
                "IP Protection"
            ],
            "monitoringAndAnalytics": [
                "Basic monitoring",
                "Usage analytics"
            ],
            "regions": [
                "Global"
            ],
            "verifiedUptime": null,
            "verifiedLatency": null,
            "verifiedBlocksBehindAvg": null,
            "starred": false,
            "actionButtons": [
                "[Website](https://www.alchemy.com/rpc/aptos-testnet)",
                "[Docs](https://www.alchemy.com/docs/reference/aptos-api-quickstart)"
            ]
        },
        {
            "slug": "alchemy-testnet-pay-as-you-go-full-archive",
            "provider": "Alchemy",
            "plan": "Pay-as-you-go",
            "nodeType": "Full Archive",
            "chain": "testnet",
            "address": null,
            "accessPrice": "$5/$45/$215/$415/$815/$2K",
            "queryPrice": "$0.40/$0.45/1M CUs",
            "uptimeSla": "99.99%",
            "bandwidthSla": null,
            "blocksBehindSla": null,
            "trial": false,
            "availableApis": [
                "eth",
                "web3",
                "net",
                "debug",
                "trace",
                "nft",
                "transfer",
                "tokens",
                "node"
            ],
            "limitations": [
                "300 req/sec"
            ],
            "securityImprovements": [
                "TX simulation",
                "DDoS Protection",
                "IP Protection",
                "SAML SSO"
            ],
            "monitoringAndAnalytics": [
                "Usage analytics",
                "Custom alerts",
                "Reporting",
                "Custom monitoring",
                "Advanced analytics"
            ],
            "regions": [
                "Global"
            ],
            "verifiedUptime": null,
            "verifiedLatency": null,
            "verifiedBlocksBehindAvg": null,
            "starred": false,
            "actionButtons": [
                "[Buy](https://www.alchemy.com/pricing)",
                "[Docs](https://www.alchemy.com/docs/reference/aptos-api-quickstart)"
            ]
        },
        {
            "slug": "alchemy-testnet-enterprise-full-archive",
            "provider": "Alchemy",
            "plan": "Enterprise",
            "nodeType": "Full Archive",
            "chain": "testnet",
            "address": null,
            "accessPrice": "Custom",
            "queryPrice": "Custom pricing",
            "uptimeSla": "99.99%",
            "bandwidthSla": null,
            "blocksBehindSla": null,
            "trial": false,
            "availableApis": [
                "eth",
                "web3",
                "net",
                "debug",
                "trace",
                "nft",
                "transfer",
                "tokens",
                "node"
            ],
            "limitations": [
                "custom limits"
            ],
            "securityImprovements": [
                "TX simulation",
                "DDoS Protection",
                "IP Protection",
                "Dedicated infrastructure"
            ],
            "monitoringAndAnalytics": [
                "Usage analytics",
                "Advanced analytics",
                "Custom dashboards",
                "Engineering support"
            ],
            "regions": [
                "Global"
            ],
            "verifiedUptime": null,
            "verifiedLatency": null,
            "verifiedBlocksBehindAvg": null,
            "starred": false,
            "actionButtons": [
                "[Contact](https://www.alchemy.com/contact-sales)",
                "[Docs](https://www.alchemy.com/docs/reference/aptos-api-quickstart)"
            ]
        },
        {
            "slug": "ankr-mainnet-free-recent-state",
            "provider": "Ankr",
            "plan": "Free",
            "nodeType": "Recent-State",
            "chain": "mainnet",
            "address": null,
            "accessPrice": "$0",
            "queryPrice": "$0",
            "uptimeSla": null,
            "bandwidthSla": null,
            "blocksBehindSla": null,
            "trial": false,
            "availableApis": [
                "Advanced ANKR API",
                "[eth](https://www.ankr.com/docs/rpc-service/chains/chains-list/)",
                "[debug](https://www.ankr.com/docs/rpc-service/chains/chains-list/)",
                "[web3](https://www.ankr.com/docs/rpc-service/chains/chains-list/)"
            ],
            "limitations": [
                "free 200M API credits/mo",
                "30 reqs/sec (node API)",
                "30 reqs/min (advanced API)",
                "1 project (personal API tokens)"
            ],
            "securityImprovements": [
                "DDoS Protection",
                "IP Protection",
                "Domain name protection",
                "Custom rate limiting",
                "Method Limiting",
                "Error tracing",
                "Contract addresses protection"
            ],
            "monitoringAndAnalytics": [
                "Usage analytics",
                "Community support"
            ],
            "regions": [
                "Global"
            ],
            "verifiedUptime": null,
            "verifiedLatency": null,
            "verifiedBlocksBehindAvg": null,
            "starred": false,
            "actionButtons": [
                "[Website](https://www.ankr.com/web3-api/chains-list/aptos/)",
                "[Docs](https://www.ankr.com/docs/rpc-service/chains/chains-api/aptos/)"
            ]
        },
        {
            "slug": "ankr-mainnet-pay-as-you-go-recent-state",
            "provider": "Ankr",
            "plan": "Pay-as-you-go",
            "nodeType": "Recent-State",
            "chain": "mainnet",
            "address": null,
            "accessPrice": "up to $10(payg plan)/$500-$3K(deal plan)",
            "queryPrice": "$0.02(evm compatible API)/$0.05(solana API)/$0.07(beacon chains API)/$0.01(other API)/$0.07(advanced API) per 1K reqs",
            "uptimeSla": null,
            "bandwidthSla": null,
            "blocksBehindSla": null,
            "trial": false,
            "availableApis": [
                "Advanced ANKR API",
                "[eth](https://www.ankr.com/docs/rpc-service/chains/chains-list/)",
                "[debug](https://www.ankr.com/docs/rpc-service/chains/chains-list/)",
                "[web3](https://www.ankr.com/docs/rpc-service/chains/chains-list/)"
            ],
            "limitations": [
                "1.5K reqs/sec (node API)",
                "1K reqs/min (advanced API)",
                "3 projects (personal API tokens)"
            ],
            "securityImprovements": [
                "DDoS Protection",
                "IP Protection",
                "Domain name protection",
                "Custom rate limiting",
                "Error tracing"
            ],
            "monitoringAndAnalytics": [
                "Usage analytics",
                "Custom monitoring",
                "Support portal"
            ],
            "regions": [
                "Global"
            ],
            "verifiedUptime": null,
            "verifiedLatency": null,
            "verifiedBlocksBehindAvg": null,
            "starred": false,
            "actionButtons": [
                "[Buy](https://www.ankr.com/web3-api/chains-list/aptos/)",
                "[Docs](https://www.ankr.com/docs/rpc-service/chains/chains-api/aptos/)"
            ]
        },
        {
            "slug": "ankr-mainnet-enterprise-recent-state",
            "provider": "Ankr",
            "plan": "Enterprise",
            "nodeType": "Recent-State",
            "chain": "mainnet",
            "address": null,
            "accessPrice": "Custom",
            "queryPrice": "custom",
            "uptimeSla": null,
            "bandwidthSla": null,
            "blocksBehindSla": null,
            "trial": false,
            "availableApis": [
                "Advanced ANKR API",
                "[eth](https://www.ankr.com/docs/rpc-service/chains/chains-list/)",
                "[debug](https://www.ankr.com/docs/rpc-service/chains/chains-list/)",
                "[web3](https://www.ankr.com/docs/rpc-service/chains/chains-list/)"
            ],
            "limitations": [
                "custom limits"
            ],
            "securityImprovements": [
                "DDoS Protection",
                "IP Protection",
                "Domain name protection",
                "Custom rate limiting",
                "Error tracing"
            ],
            "monitoringAndAnalytics": [
                "Usage analytics",
                "Custom monitoring",
                "Engineering team support"
            ],
            "regions": [
                "Global"
            ],
            "verifiedUptime": null,
            "verifiedLatency": null,
            "verifiedBlocksBehindAvg": null,
            "starred": false,
            "actionButtons": [
                "[Contact](https://meetings-eu1.hubspot.com/arsalan-evini/?uuid=a9a8ec5e-1b3d-4a78-ba96-d67ae527256a)",
                "[Docs](https://www.ankr.com/docs/rpc-service/chains/chains-api/aptos/)"
            ]
        },
        {
            "slug": "ankr-testnet-free-recent-state",
            "provider": "Ankr",
            "plan": "Free",
            "nodeType": "Recent-State",
            "chain": "testnet",
            "address": null,
            "accessPrice": "$0",
            "queryPrice": "$0",
            "uptimeSla": null,
            "bandwidthSla": null,
            "blocksBehindSla": null,
            "trial": false,
            "availableApis": [
                "Advanced ANKR API",
                "[eth](https://www.ankr.com/docs/rpc-service/chains/chains-list/)",
                "[debug](https://www.ankr.com/docs/rpc-service/chains/chains-list/)",
                "[web3](https://www.ankr.com/docs/rpc-service/chains/chains-list/)"
            ],
            "limitations": [
                "free 200M API credits/mo",
                "30 reqs/sec (node API)",
                "30 reqs/min (advanced API)",
                "1 project (personal API tokens)"
            ],
            "securityImprovements": [
                "DDoS Protection",
                "IP Protection",
                "Domain name protection",
                "Custom rate limiting",
                "Method Limiting",
                "Error tracing",
                "Contract addresses protection"
            ],
            "monitoringAndAnalytics": [
                "Usage analytics",
                "Community support"
            ],
            "regions": [
                "Global"
            ],
            "verifiedUptime": null,
            "verifiedLatency": null,
            "verifiedBlocksBehindAvg": null,
            "starred": false,
            "actionButtons": [
                "[Website](https://www.ankr.com/web3-api/chains-list/aptos/)",
                "[Docs](https://www.ankr.com/docs/rpc-service/chains/chains-api/aptos/)"
            ]
        },
        {
            "slug": "ankr-testnet-pay-as-you-go-recent-state",
            "provider": "Ankr",
            "plan": "Pay-as-you-go",
            "nodeType": "Recent-State",
            "chain": "testnet",
            "address": null,
            "accessPrice": "up to $10(payg plan)/$500-$3K(deal plan)",
            "queryPrice": "$0.02(evm compatible API)/$0.05(solana API)/$0.07(beacon chains API)/$0.01(other API)/$0.07(advanced API) per 1K reqs",
            "uptimeSla": null,
            "bandwidthSla": null,
            "blocksBehindSla": null,
            "trial": false,
            "availableApis": [
                "Advanced ANKR API",
                "[eth](https://www.ankr.com/docs/rpc-service/chains/chains-list/)",
                "[debug](https://www.ankr.com/docs/rpc-service/chains/chains-list/)",
                "[web3](https://www.ankr.com/docs/rpc-service/chains/chains-list/)"
            ],
            "limitations": [
                "1.5K reqs/sec (node API)",
                "1K reqs/min (advanced API)",
                "3 projects (personal API tokens)"
            ],
            "securityImprovements": [
                "DDoS Protection",
                "IP Protection",
                "Domain name protection",
                "Custom rate limiting",
                "Error tracing"
            ],
            "monitoringAndAnalytics": [
                "Usage analytics",
                "Custom monitoring",
                "Support portal"
            ],
            "regions": [
                "Global"
            ],
            "verifiedUptime": null,
            "verifiedLatency": null,
            "verifiedBlocksBehindAvg": null,
            "starred": false,
            "actionButtons": [
                "[Buy](https://www.ankr.com/web3-api/chains-list/aptos/)",
                "[Docs](https://www.ankr.com/docs/rpc-service/chains/chains-api/aptos/)"
            ]
        },
        {
            "slug": "ankr-testnet-enterprise-recent-state",
            "provider": "Ankr",
            "plan": "Enterprise",
            "nodeType": "Recent-State",
            "chain": "testnet",
            "address": null,
            "accessPrice": "Custom",
            "queryPrice": "custom",
            "uptimeSla": null,
            "bandwidthSla": null,
            "blocksBehindSla": null,
            "trial": false,
            "availableApis": [
                "Advanced ANKR API",
                "[eth](https://www.ankr.com/docs/rpc-service/chains/chains-list/)",
                "[debug](https://www.ankr.com/docs/rpc-service/chains/chains-list/)",
                "[web3](https://www.ankr.com/docs/rpc-service/chains/chains-list/)"
            ],
            "limitations": [
                "custom limits"
            ],
            "securityImprovements": [
                "DDoS Protection",
                "IP Protection",
                "Domain name protection",
                "Custom rate limiting",
                "Error tracing"
            ],
            "monitoringAndAnalytics": [
                "Usage analytics",
                "Custom monitoring",
                "Engineering team support"
            ],
            "regions": [
                "Global"
            ],
            "verifiedUptime": null,
            "verifiedLatency": null,
            "verifiedBlocksBehindAvg": null,
            "starred": false,
            "actionButtons": [
                "[Contact](https://meetings-eu1.hubspot.com/arsalan-evini/?uuid=a9a8ec5e-1b3d-4a78-ba96-d67ae527256a)",
                "[Docs](https://www.ankr.com/docs/rpc-service/chains/chains-api/aptos/)"
            ]
        },
        {
            "slug": "ankr-mainnet-free-full-archive",
            "provider": "Ankr",
            "plan": "Free",
            "nodeType": "Full Archive",
            "chain": "mainnet",
            "address": null,
            "accessPrice": "$0",
            "queryPrice": "$0",
            "uptimeSla": null,
            "bandwidthSla": null,
            "blocksBehindSla": null,
            "trial": false,
            "availableApis": [
                "Advanced ANKR API",
                "[eth](https://www.ankr.com/docs/rpc-service/chains/chains-list/)",
                "[debug](https://www.ankr.com/docs/rpc-service/chains/chains-list/)",
                "[web3](https://www.ankr.com/docs/rpc-service/chains/chains-list/)"
            ],
            "limitations": [
                "free 200M API credits/mo",
                "30 reqs/sec (node API)",
                "30 reqs/min (advanced API)",
                "1 project (personal API tokens)"
            ],
            "securityImprovements": [
                "DDoS Protection",
                "IP Protection",
                "Domain name protection",
                "Custom rate limiting",
                "Method Limiting",
                "Error tracing",
                "Contract addresses protection"
            ],
            "monitoringAndAnalytics": [
                "Usage analytics",
                "Community support"
            ],
            "regions": [
                "Global"
            ],
            "verifiedUptime": null,
            "verifiedLatency": null,
            "verifiedBlocksBehindAvg": null,
            "starred": false,
            "actionButtons": [
                "[Website](https://www.ankr.com/web3-api/chains-list/aptos/)",
                "[Docs](https://www.ankr.com/docs/rpc-service/chains/chains-api/aptos/)"
            ]
        },
        {
            "slug": "ankr-mainnet-pay-as-you-go-full-archive",
            "provider": "Ankr",
            "plan": "Pay-as-you-go",
            "nodeType": "Full Archive",
            "chain": "mainnet",
            "address": null,
            "accessPrice": "up to $10(payg plan)/$500-$3K(deal plan)",
            "queryPrice": "$0.02(evm compatible API)/$0.05(solana API)/$0.07(beacon chains API)/$0.01(other API)/$0.07(advanced API) per 1K reqs",
            "uptimeSla": "Custom SLA",
            "bandwidthSla": null,
            "blocksBehindSla": null,
            "trial": false,
            "availableApis": [
                "Advanced ANKR API",
                "[eth](https://www.ankr.com/docs/rpc-service/chains/chains-list/)",
                "[debug](https://www.ankr.com/docs/rpc-service/chains/chains-list/)",
                "[web3](https://www.ankr.com/docs/rpc-service/chains/chains-list/)",
                "debug",
                "trace"
            ],
            "limitations": [
                "1.5K reqs/sec (node API)",
                "1K reqs/min (advanced API)",
                "3 projects (personal API tokens)"
            ],
            "securityImprovements": [
                "DDoS Protection",
                "IP Protection",
                "Privacy preserving"
            ],
            "monitoringAndAnalytics": [
                "Usage analytics",
                "Custom monitoring",
                "Support portal"
            ],
            "regions": [
                "Global"
            ],
            "verifiedUptime": null,
            "verifiedLatency": null,
            "verifiedBlocksBehindAvg": null,
            "starred": false,
            "actionButtons": [
                "[Buy](https://www.ankr.com/web3-api/chains-list/aptos/)",
                "[Docs](https://www.ankr.com/docs/rpc-service/chains/chains-api/aptos/)"
            ]
        },
        {
            "slug": "ankr-mainnet-enterprise-full-archive",
            "provider": "Ankr",
            "plan": "Enterprise",
            "nodeType": "Full Archive",
            "chain": "mainnet",
            "address": null,
            "accessPrice": "Custom",
            "queryPrice": "custom",
            "uptimeSla": null,
            "bandwidthSla": null,
            "blocksBehindSla": null,
            "trial": false,
            "availableApis": [
                "Advanced ANKR API",
                "[eth](https://www.ankr.com/docs/rpc-service/chains/chains-list/)",
                "[debug](https://www.ankr.com/docs/rpc-service/chains/chains-list/)",
                "[web3](https://www.ankr.com/docs/rpc-service/chains/chains-list/)"
            ],
            "limitations": [
                "custom limits"
            ],
            "securityImprovements": [
                "DDoS Protection",
                "IP Protection",
                "Domain name protection",
                "Custom rate limiting",
                "Error tracing"
            ],
            "monitoringAndAnalytics": [
                "Usage analytics",
                "Custom monitoring",
                "Engineering team support"
            ],
            "regions": [
                "Global"
            ],
            "verifiedUptime": null,
            "verifiedLatency": null,
            "verifiedBlocksBehindAvg": null,
            "starred": false,
            "actionButtons": [
                "[Contact](https://meetings-eu1.hubspot.com/arsalan-evini/?uuid=a9a8ec5e-1b3d-4a78-ba96-d67ae527256a)",
                "[Docs](https://www.ankr.com/docs/rpc-service/chains/chains-api/aptos/)"
            ]
        },
        {
            "slug": "ankr-testnet-free-full-archive",
            "provider": "Ankr",
            "plan": "Free",
            "nodeType": "Full Archive",
            "chain": "testnet",
            "address": null,
            "accessPrice": "$0",
            "queryPrice": "$0",
            "uptimeSla": null,
            "bandwidthSla": null,
            "blocksBehindSla": null,
            "trial": false,
            "availableApis": [
                "Advanced ANKR API",
                "[eth](https://www.ankr.com/docs/rpc-service/chains/chains-list/)",
                "[debug](https://www.ankr.com/docs/rpc-service/chains/chains-list/)",
                "[web3](https://www.ankr.com/docs/rpc-service/chains/chains-list/)"
            ],
            "limitations": [
                "free 200M API credits/mo",
                "30 reqs/sec (node API)",
                "30 reqs/min (advanced API)",
                "1 project (personal API tokens)"
            ],
            "securityImprovements": [
                "DDoS Protection",
                "IP Protection",
                "Domain name protection",
                "Custom rate limiting",
                "Method Limiting",
                "Error tracing",
                "Contract addresses protection"
            ],
            "monitoringAndAnalytics": [
                "Usage analytics",
                "Community support"
            ],
            "regions": [
                "Global"
            ],
            "verifiedUptime": null,
            "verifiedLatency": null,
            "verifiedBlocksBehindAvg": null,
            "starred": false,
            "actionButtons": [
                "[Website](https://www.ankr.com/web3-api/chains-list/aptos/)",
                "[Docs](https://www.ankr.com/docs/rpc-service/chains/chains-api/aptos/)"
            ]
        },
        {
            "slug": "ankr-testnet-pay-as-you-go-full-archive",
            "provider": "Ankr",
            "plan": "Pay-as-you-go",
            "nodeType": "Full Archive",
            "chain": "testnet",
            "address": null,
            "accessPrice": "up to $10(payg plan)/$500-$3K(deal plan)",
            "queryPrice": "$0.02(evm compatible API)/$0.05(solana API)/$0.07(beacon chains API)/$0.01(other API)/$0.07(advanced API) per 1K reqs",
            "uptimeSla": "Custom SLA",
            "bandwidthSla": null,
            "blocksBehindSla": null,
            "trial": false,
            "availableApis": [
                "Advanced ANKR API",
                "[eth](https://www.ankr.com/docs/rpc-service/chains/chains-list/)",
                "[debug](https://www.ankr.com/docs/rpc-service/chains/chains-list/)",
                "[web3](https://www.ankr.com/docs/rpc-service/chains/chains-list/)",
                "debug",
                "trace"
            ],
            "limitations": [
                "1.5K reqs/sec (node API)",
                "1K reqs/min (advanced API)",
                "3 projects (personal API tokens)"
            ],
            "securityImprovements": [
                "DDoS Protection",
                "IP Protection",
                "Privacy preserving"
            ],
            "monitoringAndAnalytics": [
                "Usage analytics",
                "Custom monitoring",
                "Support portal"
            ],
            "regions": [
                "Global"
            ],
            "verifiedUptime": null,
            "verifiedLatency": null,
            "verifiedBlocksBehindAvg": null,
            "starred": false,
            "actionButtons": [
                "[Buy](https://www.ankr.com/web3-api/chains-list/aptos/)",
                "[Docs](https://www.ankr.com/docs/rpc-service/chains/chains-api/aptos/)"
            ]
        },
        {
            "slug": "ankr-testnet-enterprise-full-archive",
            "provider": "Ankr",
            "plan": "Enterprise",
            "nodeType": "Full Archive",
            "chain": "testnet",
            "address": null,
            "accessPrice": "Custom",
            "queryPrice": "custom",
            "uptimeSla": null,
            "bandwidthSla": null,
            "blocksBehindSla": null,
            "trial": false,
            "availableApis": [
                "Advanced ANKR API",
                "[eth](https://www.ankr.com/docs/rpc-service/chains/chains-list/)",
                "[debug](https://www.ankr.com/docs/rpc-service/chains/chains-list/)",
                "[web3](https://www.ankr.com/docs/rpc-service/chains/chains-list/)"
            ],
            "limitations": [
                "custom limits"
            ],
            "securityImprovements": [
                "DDoS Protection",
                "IP Protection",
                "Domain name protection",
                "Custom rate limiting",
                "Error tracing"
            ],
            "monitoringAndAnalytics": [
                "Usage analytics",
                "Custom monitoring",
                "Engineering team support"
            ],
            "regions": [
                "Global"
            ],
            "verifiedUptime": null,
            "verifiedLatency": null,
            "verifiedBlocksBehindAvg": null,
            "starred": false,
            "actionButtons": [
                "[Contact](https://meetings-eu1.hubspot.com/arsalan-evini/?uuid=a9a8ec5e-1b3d-4a78-ba96-d67ae527256a)",
                "[Docs](https://www.ankr.com/docs/rpc-service/chains/chains-api/aptos/)"
            ]
        },
        {
            "slug": "chainstack-mainnet-free-recent-state",
            "provider": "ChainStack",
            "plan": "Free",
            "nodeType": "Recent-State",
            "chain": "mainnet",
            "address": null,
            "accessPrice": "$0",
            "queryPrice": "$20/1M extra requests",
            "uptimeSla": "99.90%",
            "bandwidthSla": null,
            "blocksBehindSla": null,
            "trial": false,
            "availableApis": [
                "eth",
                "web3",
                "net"
            ],
            "limitations": [
                "25 RPS",
                "3M requests/mo"
            ],
            "securityImprovements": [
                "DDoS Protection",
                "IP Protection"
            ],
            "monitoringAndAnalytics": [
                "Usage analytics",
                "Basic monitoring"
            ],
            "regions": [
                "Global"
            ],
            "verifiedUptime": null,
            "verifiedLatency": null,
            "verifiedBlocksBehindAvg": null,
            "starred": false,
            "actionButtons": [
                "[Website](https://chainstack.com/build-better-with-aptos/)",
                "[Docs](https://docs.chainstack.com/docs/aptos-methods)"
            ]
        },
        {
            "slug": "chainstack-mainnet-pay-as-you-go-recent-state",
            "provider": "ChainStack",
            "plan": "Pay-as-you-go",
            "nodeType": "Recent-State",
            "chain": "mainnet",
            "address": null,
            "accessPrice": "$49/$199/$349/mo (monthly plan), $40/$166/$290/mo (yearly plan)",
            "queryPrice": "$15/$12.5/$10 per 1M extra requests",
            "uptimeSla": "99.90%",
            "bandwidthSla": null,
            "blocksBehindSla": null,
            "trial": false,
            "availableApis": [
                "eth",
                "web3",
                "net",
                "debug",
                "trace"
            ],
            "limitations": [
                "250/400/600 RPS",
                "20M/80M/140M requests",
                "10,15,20 nodes"
            ],
            "securityImprovements": [
                "DDoS Protection",
                "IP Protection",
                "Dedicated infrastructure"
            ],
            "monitoringAndAnalytics": [
                "Usage analytics",
                "Custom monitoring",
                "Engineering team support"
            ],
            "regions": [
                "Global"
            ],
            "verifiedUptime": null,
            "verifiedLatency": null,
            "verifiedBlocksBehindAvg": null,
            "starred": false,
            "actionButtons": [
                "[Buy](https://chainstack.com/pricing/)",
                "[Docs](https://docs.chainstack.com/docs/aptos-methods)"
            ]
        },
        {
            "slug": "chainstack-mainnet-enterprise-recent-state",
            "provider": "ChainStack",
            "plan": "Enterprise",
            "nodeType": "Recent-State",
            "chain": "mainnet",
            "address": null,
            "accessPrice": "up to $990/mo (monthly plan), up to $825/mo (yearly plan)",
            "queryPrice": "$5/1M extra requests",
            "uptimeSla": "99.99%",
            "bandwidthSla": null,
            "blocksBehindSla": null,
            "trial": false,
            "availableApis": [
                "eth",
                "web3",
                "net",
                "debug",
                "trace"
            ],
            "limitations": [
                "400M requests"
            ],
            "securityImprovements": [
                "DDoS Protection",
                "IP Protection",
                "Dedicated infrastructure"
            ],
            "monitoringAndAnalytics": [
                "Advanced analytics",
                "Custom monitoring"
            ],
            "regions": [
                "Global"
            ],
            "verifiedUptime": null,
            "verifiedLatency": null,
            "verifiedBlocksBehindAvg": null,
            "starred": false,
            "actionButtons": [
                "[Contact](https://console.chainstack.com/user/account#login)",
                "[Docs](https://docs.chainstack.com/docs/aptos-methods)"
            ]
        },
        {
            "slug": "chainstack-testnet-free-recent-state",
            "provider": "ChainStack",
            "plan": "Free",
            "nodeType": "Recent-State",
            "chain": "testnet",
            "address": null,
            "accessPrice": "$0",
            "queryPrice": "$20/1M extra requests",
            "uptimeSla": "99.90%",
            "bandwidthSla": null,
            "blocksBehindSla": null,
            "trial": false,
            "availableApis": [
                "eth",
                "web3",
                "net"
            ],
            "limitations": [
                "25 RPS",
                "3M requests/mo"
            ],
            "securityImprovements": [
                "DDoS Protection",
                "IP Protection"
            ],
            "monitoringAndAnalytics": [
                "Usage analytics",
                "Basic monitoring"
            ],
            "regions": [
                "Global"
            ],
            "verifiedUptime": null,
            "verifiedLatency": null,
            "verifiedBlocksBehindAvg": null,
            "starred": false,
            "actionButtons": [
                "[Website](https://chainstack.com/build-better-with-aptos/)",
                "[Docs](https://docs.chainstack.com/docs/aptos-methods)"
            ]
        },
        {
            "slug": "chainstack-testnet-pay-as-you-go-recent-state",
            "provider": "ChainStack",
            "plan": "Pay-as-you-go",
            "nodeType": "Recent-State",
            "chain": "testnet",
            "address": null,
            "accessPrice": "$49/$199/$349/mo (monthly plan), $40/$166/$290/mo (yearly plan)",
            "queryPrice": "$15/$12.5/$10 per 1M extra requests",
            "uptimeSla": "99.90%",
            "bandwidthSla": null,
            "blocksBehindSla": null,
            "trial": false,
            "availableApis": [
                "eth",
                "web3",
                "net",
                "debug",
                "trace"
            ],
            "limitations": [
                "250/400/600 RPS",
                "20M/80M/140M requests",
                "10,15,20 nodes"
            ],
            "securityImprovements": [
                "DDoS Protection",
                "IP Protection",
                "Dedicated infrastructure"
            ],
            "monitoringAndAnalytics": [
                "Usage analytics",
                "Custom monitoring",
                "Engineering team support"
            ],
            "regions": [
                "Global"
            ],
            "verifiedUptime": null,
            "verifiedLatency": null,
            "verifiedBlocksBehindAvg": null,
            "starred": false,
            "actionButtons": [
                "[Buy](https://chainstack.com/pricing/)",
                "[Docs](https://docs.chainstack.com/docs/aptos-methods)"
            ]
        },
        {
            "slug": "chainstack-testnet-enterprise-recent-state",
            "provider": "ChainStack",
            "plan": "Enterprise",
            "nodeType": "Recent-State",
            "chain": "testnet",
            "address": null,
            "accessPrice": "up to $990/mo (monthly plan), up to $825/mo (yearly plan)",
            "queryPrice": "$5/1M extra requests",
            "uptimeSla": "99.99%",
            "bandwidthSla": null,
            "blocksBehindSla": null,
            "trial": false,
            "availableApis": [
                "eth",
                "web3",
                "net",
                "debug",
                "trace"
            ],
            "limitations": [
                "400M requests"
            ],
            "securityImprovements": [
                "DDoS Protection",
                "IP Protection",
                "Dedicated infrastructure"
            ],
            "monitoringAndAnalytics": [
                "Advanced analytics",
                "Custom monitoring"
            ],
            "regions": [
                "Global"
            ],
            "verifiedUptime": null,
            "verifiedLatency": null,
            "verifiedBlocksBehindAvg": null,
            "starred": false,
            "actionButtons": [
                "[Contact](https://console.chainstack.com/user/account#login)",
                "[Docs](https://docs.chainstack.com/docs/aptos-methods)"
            ]
        },
        {
            "slug": "chainstack-mainnet-pay-as-you-go-full-archive",
            "provider": "ChainStack",
            "plan": "Pay-as-you-go",
            "nodeType": "Full Archive",
            "chain": "mainnet",
            "address": null,
            "accessPrice": "$49/$199/$349/mo (monthly plan), $40/$166/$290/mo (yearly plan)",
            "queryPrice": "$15/$12.5/$10 per 1M extra requests",
            "uptimeSla": "99.90%",
            "bandwidthSla": null,
            "blocksBehindSla": null,
            "trial": false,
            "availableApis": [
                "eth",
                "web3",
                "net",
                "debug",
                "trace"
            ],
            "limitations": [
                "250/400/600 RPS",
                "20M/80M/140M requests",
                "10,15,20 nodes"
            ],
            "securityImprovements": [
                "DDoS Protection",
                "IP Protection",
                "Dedicated infrastructure"
            ],
            "monitoringAndAnalytics": [
                "Usage analytics",
                "Custom monitoring",
                "Engineering team support"
            ],
            "regions": [
                "Global"
            ],
            "verifiedUptime": null,
            "verifiedLatency": null,
            "verifiedBlocksBehindAvg": null,
            "starred": false,
            "actionButtons": [
                "[Buy](https://chainstack.com/pricing/)",
                "[Docs](https://docs.chainstack.com/docs/aptos-methods)"
            ]
        },
        {
            "slug": "chainstack-mainnet-enterprise-full-archive",
            "provider": "ChainStack",
            "plan": "Enterprise",
            "nodeType": "Full Archive",
            "chain": "mainnet",
            "address": null,
            "accessPrice": "up to $990/mo (monthly plan), up to $825/mo (yearly plan)",
            "queryPrice": "$5/1M extra requests",
            "uptimeSla": "99.99%",
            "bandwidthSla": null,
            "blocksBehindSla": null,
            "trial": true,
            "availableApis": [
                "eth",
                "web3",
                "net",
                "debug",
                "trace"
            ],
            "limitations": [
                "400M requests"
            ],
            "securityImprovements": [
                "DDoS Protection",
                "IP Protection",
                "Dedicated infrastructure"
            ],
            "monitoringAndAnalytics": [
                "Advanced analytics",
                "Custom monitoring"
            ],
            "regions": [
                "Global"
            ],
            "verifiedUptime": null,
            "verifiedLatency": null,
            "verifiedBlocksBehindAvg": null,
            "starred": false,
            "actionButtons": [
                "[Contact](https://console.chainstack.com/user/account#login)",
                "[Docs](https://docs.chainstack.com/docs/aptos-methods)"
            ]
        },
        {
            "slug": "chainstack-testnet-pay-as-you-go-full-archive",
            "provider": "ChainStack",
            "plan": "Pay-as-you-go",
            "nodeType": "Full Archive",
            "chain": "testnet",
            "address": null,
            "accessPrice": "$49/$199/$349/mo (monthly plan), $40/$166/$290/mo (yearly plan)",
            "queryPrice": "$15/$12.5/$10 per 1M extra requests",
            "uptimeSla": "99.90%",
            "bandwidthSla": null,
            "blocksBehindSla": null,
            "trial": false,
            "availableApis": [
                "eth",
                "web3",
                "net",
                "debug",
                "trace"
            ],
            "limitations": [
                "250/400/600 RPS",
                "20M/80M/140M requests",
                "10,15,20 nodes"
            ],
            "securityImprovements": [
                "DDoS Protection",
                "IP Protection",
                "Dedicated infrastructure"
            ],
            "monitoringAndAnalytics": [
                "Usage analytics",
                "Custom monitoring",
                "Engineering team support"
            ],
            "regions": [
                "Global"
            ],
            "verifiedUptime": null,
            "verifiedLatency": null,
            "verifiedBlocksBehindAvg": null,
            "starred": false,
            "actionButtons": [
                "[Buy](https://chainstack.com/pricing/)",
                "[Docs](https://docs.chainstack.com/docs/aptos-methods)"
            ]
        },
        {
            "slug": "chainstack-testnet-enterprise-full-archive",
            "provider": "ChainStack",
            "plan": "Enterprise",
            "nodeType": "Full Archive",
            "chain": "testnet",
            "address": null,
            "accessPrice": "up to $990/mo (monthly plan), up to $825/mo (yearly plan)",
            "queryPrice": "$5/1M extra requests",
            "uptimeSla": "99.99%",
            "bandwidthSla": null,
            "blocksBehindSla": null,
            "trial": true,
            "availableApis": [
                "eth",
                "web3",
                "net",
                "debug",
                "trace"
            ],
            "limitations": [
                "400M requests"
            ],
            "securityImprovements": [
                "DDoS Protection",
                "IP Protection",
                "Dedicated infrastructure"
            ],
            "monitoringAndAnalytics": [
                "Advanced analytics",
                "Custom monitoring"
            ],
            "regions": [
                "Global"
            ],
            "verifiedUptime": null,
            "verifiedLatency": null,
            "verifiedBlocksBehindAvg": null,
            "starred": false,
            "actionButtons": [
                "[Contact](https://console.chainstack.com/user/account#login)",
                "[Docs](https://docs.chainstack.com/docs/aptos-methods)"
            ]
        }
    ],
    "faucet": [
        {
            "slug": "stakely-faucet",
            "provider": "Stakely",
            "chain": "mainnet",
            "requiresLogin": false,
            "hasCaptcha": true,
            "requiredMainnetBalance": null,
            "price": "$0",
            "dripLimitAmount": "0.00088 APT",
            "dripLimitPeriod": null,
            "additionalNotes": [
                "Requires to make the tweet in X about requesting tokens",
                "Need to have low or zero mainnet balance for asking mainnet tokens"
            ],
            "starred": false,
            "actionButtons": [
                "[Faucet](https://stakely.io/faucet/aptos-apt)"
            ]
        },
        {
            "slug": "circle-faucet-usdc",
            "provider": "Circle",
            "chain": "testnet",
            "requiresLogin": false,
            "hasCaptcha": false,
            "requiredMainnetBalance": null,
            "price": "$0",
            "dripLimitAmount": "1 USDC",
            "dripLimitPeriod": "1h",
            "additionalNotes": null,
            "starred": false,
            "actionButtons": [
                "[Faucet](https://faucet.circle.com/)"
            ]
        }
    ],
    "wallet": [
        {
            "slug": "trustwallet",
            "provider": "Trust Wallet",
            "openSource": false,
            "supportedPlatforms": [
                "iOS",
                "Android",
                "Chrome"
            ],
            "custodial": false,
            "mfa": true,
            "msig": false,
            "hardware": false,
            "keyExport": true,
            "native": false,
            "evm": true,
            "tendermint": false,
            "tokensSupport": [
                "ERC-20",
                "ERC-721",
                "ERC-1155"
            ],
            "staking": true,
            "price": "$0",
            "support": [
                "email",
                "helpdesk"
            ],
            "audit": null,
            "languages": [
                "EN",
                "ES",
                "FR",
                "ZH",
                "JA"
            ],
            "starred": false,
            "actionButtons": [
                "[Website](https://trustwallet.com/)"
            ]
        },
        {
            "slug": "onekey",
            "provider": "OneKey",
            "openSource": true,
            "supportedPlatforms": [
                "Desktop",
                "iOS",
                "Android",
                "Chrome"
            ],
            "custodial": false,
            "mfa": true,
            "msig": true,
            "hardware": true,
            "keyExport": true,
            "native": false,
            "evm": true,
            "tendermint": true,
            "tokensSupport": [
                "ERC-20",
                "ERC-721",
                "EIP-721",
                "EIP-1155",
                "SPL",
                "Algorand Standard Assets (ASA)"
            ],
            "staking": true,
            "price": "$0",
            "support": [
                "[email](hi@onekey.so)",
                "support website",
                "x",
                "github"
            ],
            "audit": null,
            "languages": [
                "EN",
                "FR",
                "PT",
                "PT-Br",
                "RU",
                "DE",
                "ES",
                "IT",
                "ID",
                "ZH",
                "KO",
                "UA",
                "VI",
                "HI",
                "JA"
            ],
            "starred": false,
            "actionButtons": [
                "[Website](https://onekey.so/)"
            ]
        },
        {
            "slug": "exodus",
            "provider": "Exodus",
            "openSource": true,
            "supportedPlatforms": [
                "Desktop",
                "iOS",
                "Android",
                "Chrome"
            ],
            "custodial": false,
            "mfa": false,
            "msig": false,
            "hardware": true,
            "keyExport": true,
            "native": false,
            "evm": true,
            "tendermint": true,
            "tokensSupport": [
                "ERC-20",
                "BEP-20",
                "TRC-20",
                "SPL",
                "Algorand Standard Assets (ASA)"
            ],
            "staking": true,
            "price": "$0",
            "support": [
                "[x](@ExodusAssist)",
                "helpdesk",
                "email"
            ],
            "audit": null,
            "languages": [
                "EN",
                "ES"
            ],
            "starred": false,
            "actionButtons": [
                "[Website](https://www.exodus.com/)"
            ]
        }
    ],
    "columns": {
        "rpc": [
            "slug",
            "provider",
            "plan",
            "nodeType",
            "chain",
            "address",
            "accessPrice",
            "queryPrice",
            "uptimeSla",
            "bandwidthSla",
            "blocksBehindSla",
            "trial",
            "availableApis",
            "limitations",
            "securityImprovements",
            "monitoringAndAnalytics",
            "regions",
            "verifiedUptime",
            "verifiedLatency",
            "verifiedBlocksBehindAvg",
            "starred",
            "actionButtons"
        ],
        "faucet": [
            "slug",
            "provider",
            "chain",
            "requiresLogin",
            "hasCaptcha",
            "requiredMainnetBalance",
            "price",
            "dripLimitAmount",
            "dripLimitPeriod",
            "additionalNotes",
            "starred",
            "actionButtons"
        ],
        "wallet": [
            "slug",
            "provider",
            "openSource",
            "supportedPlatforms",
            "custodial",
            "mfa",
            "msig",
            "hardware",
            "keyExport",
            "native",
            "evm",
            "tendermint",
            "tokensSupport",
            "staking",
            "price",
            "support",
            "audit",
            "languages",
            "starred",
            "actionButtons"
        ]
    }
}